[
  {
    "context": "icecream",
    "nameSpace": "XM",
    "type": "IceCreamFlavor",
    "table": "ic.icflav",
    "idSequenceName": "ic.icflav_icflav_id_seq",
    "lockable": true,
    "comment": "Ice Cream Flavor Map",
    "privileges": {
      "all": {
        "create": "MaintainIceCreamFlavors",
        "read": true,
        "update": "MaintainIceCreamFlavors",
        "delete": "MaintainIceCreamFlavors"
      }
    },
    "properties": [
      {
        "name": "id",
        "attr": {
          "type": "Number",
          "column": "icflav_id",
          "isPrimaryKey": true
        }
      },
      {
        "name": "name",
        "attr": {
          "type": "String",
          "column": "icflav_name",
          "isNaturalKey": true
        }
      },
      {
        "name": "description",
        "attr": {
          "type": "String",
          "column": "icflav_description"
        }
      },
      {
        "name": "calories",
        "attr": {
          "type": "Number",
          "column": "icflav_calories"
        }
      }
    ],
    "isSystem": true
  }
]
